qingcloudrc/__init__.py
qingcloudrc/qingcloudrc.py
qingcloudrc-0.0.1.dist-info/DESCRIPTION.rst
qingcloudrc-0.0.1.dist-info/METADATA
qingcloudrc-0.0.1.dist-info/RECORD
qingcloudrc-0.0.1.dist-info/WHEEL
qingcloudrc-0.0.1.dist-info/entry_points.txt
qingcloudrc-0.0.1.dist-info/metadata.json
qingcloudrc-0.0.1.dist-info/top_level.txt
qingcloudrc-0.0.1.dist-info/zip-safe
