Metadata-Version: 2.0
Name: qingcloudrc
Version: 0.0.1
Summary: Python
Home-page: https://github.com/xxx
Author: ztt
Author-email: zttjava@qq.com
License: MIT
Keywords: python
Platform: UNKNOWN
